siwi/__init__.py
siwi/app/__init__.py
siwi/app/app.py
siwi/bot/__init__.py
siwi/bot/actions/__init__.py
siwi/bot/bot/__init__.py
siwi/bot/classifier/__init__.py
siwi/bot/test/data/example_intents.yaml
siwi/bot/test/data/example_players.yaml
siwi/bot/test/data/example_teams.yaml
siwi-0.3.2.dist-info/METADATA
siwi-0.3.2.dist-info/WHEEL
siwi-0.3.2.dist-info/top_level.txt
siwi-0.3.2.dist-info/RECORD
