Metadata-Version: 2.1
Name: siwi
Version: 0.3.2
Summary: A PoC of Dialog System With Graph Database Backed Knowledge Graph.
Home-page: https://github.com/wey-gu/nebula-siwi
Author: Wey Gu
Author-email: weyl.gu@gmail.com
Project-URL: Bug Tracker, https://github.com/wey-gu/nebula-siwi/issues
Classifier: Intended Audience :: Developers
Classifier: Programming Language :: Python :: 3
Classifier: License :: OSI Approved :: Apache Software License
Classifier: Operating System :: OS Independent
Requires-Python: >=3.6
Requires-Dist: nebula3-python
Requires-Dist: pyahocorasick
Requires-Dist: pyyaml
Requires-Dist: flask
Requires-Dist: gunicorn
